gpustack_runtime/__init__.py
gpustack_runtime/__main__.py
gpustack_runtime/_version.py
gpustack_runtime/_version.pyi
gpustack_runtime/envs.py
gpustack_runtime/logging.py
gpustack_runtime/cmds/__init__.py
gpustack_runtime/cmds/__types__.py
gpustack_runtime/cmds/deployer.py
gpustack_runtime/cmds/detector.py
gpustack_runtime/cmds/images.py
gpustack_runtime/deployer/__init__.py
gpustack_runtime/deployer/__patches__.py
gpustack_runtime/deployer/__types__.py
gpustack_runtime/deployer/__utils__.py
gpustack_runtime/deployer/docker.py
gpustack_runtime/deployer/kuberentes.py
gpustack_runtime/deployer/podman.py
gpustack_runtime/deployer/cdi/__init__.py
gpustack_runtime/deployer/cdi/__types__.py
gpustack_runtime/deployer/cdi/__utils__.py
gpustack_runtime/deployer/cdi/amd.py
gpustack_runtime/deployer/cdi/ascend.py
gpustack_runtime/deployer/cdi/hygon.py
gpustack_runtime/deployer/cdi/iluvatar.py
gpustack_runtime/deployer/cdi/metax.py
gpustack_runtime/deployer/cdi/thead.py
gpustack_runtime/deployer/k8s/deviceplugin/__init__.py
gpustack_runtime/deployer/k8s/deviceplugin/__types__.py
gpustack_runtime/deployer/k8s/deviceplugin/plugin.py
gpustack_runtime/deployer/k8s/types/kubelet/deviceplugin/v1beta1/__init__.py
gpustack_runtime/deployer/k8s/types/kubelet/deviceplugin/v1beta1/api.proto
gpustack_runtime/deployer/k8s/types/kubelet/deviceplugin/v1beta1/api_pb2.py
gpustack_runtime/deployer/k8s/types/kubelet/deviceplugin/v1beta1/api_pb2.pyi
gpustack_runtime/deployer/k8s/types/kubelet/deviceplugin/v1beta1/api_pb2_grpc.py
gpustack_runtime/deployer/k8s/types/kubelet/deviceplugin/v1beta1/constants.py
gpustack_runtime/detector/__init__.py
gpustack_runtime/detector/__types__.py
gpustack_runtime/detector/__utils__.py
gpustack_runtime/detector/amd.py
gpustack_runtime/detector/ascend.py
gpustack_runtime/detector/cambricon.py
gpustack_runtime/detector/hygon.py
gpustack_runtime/detector/iluvatar.py
gpustack_runtime/detector/metax.py
gpustack_runtime/detector/mthreads.py
gpustack_runtime-0.1.41.post3.dist-info/METADATA
gpustack_runtime-0.1.41.post3.dist-info/WHEEL
gpustack_runtime-0.1.41.post3.dist-info/entry_points.txt
gpustack_runtime-0.1.41.post3.dist-info/licenses/LICENSE
gpustack_runtime-0.1.41.post3.dist-info/RECORD
