Metadata-Version: 2.4
Name: gpustack-runtime
Version: 0.1.41.post3
Summary: GPUStack Runtime is library for detecting GPU resources and launching GPU workloads.
Project-URL: Homepage, https://github.com/gpustack/runtime
Project-URL: Bug Tracker, https://github.com/gpustack/gpustack/issues
Author-email: GPUStack Authors <contact@gpustack.ai>
License-Expression: Apache-2.0
License-File: LICENSE
Classifier: Programming Language :: Python :: 3
Classifier: Programming Language :: Python :: 3.10
Classifier: Programming Language :: Python :: 3.11
Classifier: Programming Language :: Python :: 3.12
Classifier: Programming Language :: Python :: 3.13
Requires-Python: >=3.10
Requires-Dist: argcomplete>=3.6.3
Requires-Dist: cachetools>=5.5.2
Requires-Dist: docker>=7.1.0
Requires-Dist: gpustack-runner>=0.1.24.post1
Requires-Dist: grpc-interceptor>=0.15.4
Requires-Dist: grpcio>=1.76.0
Requires-Dist: kubernetes>=33.1.0
Requires-Dist: mthreads-ml-py>=2.2.10
Requires-Dist: nvidia-ml-py>=13.580.65
Requires-Dist: podman==5.6.0
Requires-Dist: protobuf<=3.19.6
Requires-Dist: pyyaml
Requires-Dist: tqdm
Requires-Dist: types-protobuf<=5.28.3.20241203
